setup.cfg
setup.py
connector/__init__.py
connector/connector.py
ipcu/__init__.py
ipcu/ipcu.py
ipcu_connections.egg-info/PKG-INFO
ipcu_connections.egg-info/SOURCES.txt
ipcu_connections.egg-info/dependency_links.txt
ipcu_connections.egg-info/not-zip-safe
ipcu_connections.egg-info/top_level.txt
urlib/__init__.py
urlib/urlib.py