Metadata-Version: 1.0
Name: ipcu-connections
Version: 0.0
Summary: IPCU
Home-page: UNKNOWN
Author: UNKNOWN
Author-email: morin.aleksa@gmail.com
License: UNKNOWN
Platform: UNKNOWN
